earthdaily/earthone/dynamic_compute/__init__.py
earthdaily/earthone/dynamic_compute/catalog/__init__.py
earthdaily/earthone/dynamic_compute/catalog/blob.py
earthdaily/earthone/dynamic_compute/compute_map.py
earthdaily/earthone/dynamic_compute/datetime_utils.py
earthdaily/earthone/dynamic_compute/dot.py
earthdaily/earthone/dynamic_compute/dynamic_compute.py
earthdaily/earthone/dynamic_compute/eo_utils.py
earthdaily/earthone/dynamic_compute/geofencing.py
earthdaily/earthone/dynamic_compute/graft/__init__.py
earthdaily/earthone/dynamic_compute/graft/client/__init__.py
earthdaily/earthone/dynamic_compute/graft/client/client.py
earthdaily/earthone/dynamic_compute/graft/interpreter/__init__.py
earthdaily/earthone/dynamic_compute/graft/interpreter/exceptions.py
earthdaily/earthone/dynamic_compute/graft/interpreter/interpreter.py
earthdaily/earthone/dynamic_compute/graft/interpreter/scopedchainmap.py
earthdaily/earthone/dynamic_compute/graft/spec.md
earthdaily/earthone/dynamic_compute/graft/syntax/__init__.py
earthdaily/earthone/dynamic_compute/graft/syntax/syntax.py
earthdaily/earthone/dynamic_compute/groupby.py
earthdaily/earthone/dynamic_compute/image_stack.py
earthdaily/earthone/dynamic_compute/interactive/__init__.py
earthdaily/earthone/dynamic_compute/interactive/clearable.py
earthdaily/earthone/dynamic_compute/interactive/colormaps.py
earthdaily/earthone/dynamic_compute/interactive/inspector.py
earthdaily/earthone/dynamic_compute/interactive/layer.py
earthdaily/earthone/dynamic_compute/interactive/layer_controller.py
earthdaily/earthone/dynamic_compute/interactive/layer_controller_row.py
earthdaily/earthone/dynamic_compute/interactive/lonlat.py
earthdaily/earthone/dynamic_compute/interactive/map_.py
earthdaily/earthone/dynamic_compute/interactive/tile_url.py
earthdaily/earthone/dynamic_compute/interactive/utils.py
earthdaily/earthone/dynamic_compute/mosaic.py
earthdaily/earthone/dynamic_compute/operations.py
earthdaily/earthone/dynamic_compute/proxies.py
earthdaily_earthone_dynamic_compute-2.2.1.dist-info/METADATA
earthdaily_earthone_dynamic_compute-2.2.1.dist-info/WHEEL
earthdaily_earthone_dynamic_compute-2.2.1.dist-info/licenses/LICENSE
earthdaily_earthone_dynamic_compute-2.2.1.dist-info/RECORD
