Metadata-Version: 2.4
Name: earthdaily-earthone-dynamic-compute
Version: 2.2.1
Summary: 
License: Apache-2.0
License-File: LICENSE
Author: EarthDaily
Requires-Python: >=3.10,<3.13
Classifier: License :: OSI Approved :: Apache Software License
Classifier: Programming Language :: Python :: 3
Classifier: Programming Language :: Python :: 3.10
Classifier: Programming Language :: Python :: 3.11
Classifier: Programming Language :: Python :: 3.12
Requires-Dist: blosc2 (>=3.10.1,<4.0.0)
Requires-Dist: certifi (>=2023.7.22)
Requires-Dist: cloudpickle (==3.0.0)
Requires-Dist: earthdaily-earthone (>=5,<6)
Requires-Dist: geojson (>=2.5.0)
Requires-Dist: imagecodecs (<=2023.3.16) ; python_version < "3.12"
Requires-Dist: imagecodecs (>=2023.7.4) ; python_version >= "3.12"
Requires-Dist: ipyleaflet (>=0.15.0)
Requires-Dist: matplotlib (>3.6)
Requires-Dist: numpy (<3) ; python_version >= "3.11"
Requires-Dist: numpy (<=2.0.2) ; python_version < "3.11"
Requires-Dist: pandas (>=2.2)
Requires-Dist: pyproj (<=3.4.1) ; python_version < "3.12"
Requires-Dist: pyproj (>=3.6.1) ; python_version >= "3.12"
Requires-Dist: pyzmq (<=26.0.3) ; python_version < "3.12"
Requires-Dist: pyzmq (>=25.1.1) ; python_version >= "3.12"
Requires-Dist: shapely (>2,<3)
Requires-Dist: utm (>=0.7.0,<0.8.0)
